__init__.py
classes.py
hdf5_read_test.py
hdf5_write_test.py
helpers.py
plotly_test.py
psp_liquids_daq_parser.py
tdms_test.py
testfile.py
psp_liquids_daq_parser-0.0.20.dist-info/LICENSE
psp_liquids_daq_parser-0.0.20.dist-info/METADATA
psp_liquids_daq_parser-0.0.20.dist-info/WHEEL
psp_liquids_daq_parser-0.0.20.dist-info/top_level.txt
psp_liquids_daq_parser-0.0.20.dist-info/RECORD
