Metadata-Version: 2.1
Name: psp_liquids_daq_parser
Version: 0.0.20
Summary: Used to parse, convert, pickle, and pre-process TDMS files from BCLS or other NI daq boxes.
Author-email: Rajan Phadnis <rajansd28@gmail.com>
Project-URL: Homepage, https://github.com/Purdue-Space-Program/daq_parser
Project-URL: Issues, https://github.com/Purdue-Space-Program/daq_parser/issues
Classifier: Programming Language :: Python :: 3.11
Classifier: License :: OSI Approved :: GNU General Public License v3 (GPLv3)
Classifier: Operating System :: OS Independent
Requires-Python: >=3.11.0
License-File: LICENSE
Requires-Dist: npTDMS[hdf,pandas,thermocouple_scaling] >=1.9.0
Requires-Dist: numpy >=1.26.4
